{
    "standing": [
        {
            "impact": "10",
            "input": "1,4",
            "damage": "21",
            "hit": "+4",
            "notes": ""
        },

        {
            "impact": "10",
            "input": "2,3",
            "damage": "24",
            "hit": "+6",
            "notes": "Shorter range than 1,4"
        },

        {
            "impact": "12",
            "input": "4,3",
            "damage": "27",
            "hit": "+2",
            "notes": ""
        },

        {
            "impact": "13",
            "input": "d/f+2,1",
            "damage": "23",
            "hit": "+8",
            "notes": ""
        },

        {
            "impact": "14",
            "input": "f,b+2",
            "damage": "20",
            "hit": "Launch",
            "notes": ""
        },

        {
            "impact": "14",
            "input": "f,F+2",
            "damage": "32",
            "hit": "KND",
            "notes": "Long range, hard"
        },

        {
            "impact": "15",
            "input": "f+2,1,4",
            "damage": "42",
            "hit": "KND",
            "notes": "Mid, Wall Break"
        },

        {
            "impact": "16",
            "input": "b+4",
            "damage": "18",
            "hit": "+15",
            "notes": "Wall Punish, Guaranteed f,b+2 or f,F+2"
        },

        {
            "impact": "18",
            "input": "f+4,1",
            "damage": "20",
            "hit": "Launch",
            "notes": "Long range"
        },

        {
            "impact": "18",
            "input": "in rage b+1+2",
            "damage": "30",
            "hit": "Launch",
            "notes": "Rage, Long range"
        }

    ],

    "crouching": [
        {
            "impact": "10",
            "input": "FC+1",
            "damage": "5",
            "hit": "+6",
            "notes": "Generic"
        },

        {
            "impact": "11",
            "input": "WS+4",
            "damage": "16",
            "hit": "+5",
            "notes": ""
        },

        {
            "impact": "12",
            "input": "WS+3",
            "damage": "18",
            "hit": "+4",
            "notes": ""
        },

        {
            "impact": "13",
            "input": "FC+d/f+2,1",
            "damage": "37",
            "hit": "KND",
            "notes": "Wall Splat, Wall Break"
        },
        
        {
            "impact": "15",
            "input": "WS+1",
            "damage": "20",
            "hit": "Launch",
            "notes": ""
        },
        
        {
            "impact": "19",
            "input": "WS+2, f+2",
            "damage": "43",
            "hit": "Launch",
            "notes": "Switches Side, can be inputted with WS+2, b+2"
        }
    ]
}